http_server/__init__.py
http_server/server.py
http_server/templates/base.template
http_server/templates/file.template
http_server/templates/listing.template
beautify_http_server-0.0.1.dist-info/LICENSE
beautify_http_server-0.0.1.dist-info/METADATA
beautify_http_server-0.0.1.dist-info/WHEEL
beautify_http_server-0.0.1.dist-info/entry_points.txt
beautify_http_server-0.0.1.dist-info/top_level.txt
beautify_http_server-0.0.1.dist-info/RECORD
