Metadata-Version: 2.1
Name: beautify-http-server
Version: 0.0.1
Summary: (Beautiful) replacement for the 'http.server' Python3 module. Allows file upload, preview and much more.
Author-email: Lorenzo Di Fuccia <lorenzo.difuccia@gmail.com>
License: Apache-2.0
Project-URL: Homepage, https://github.com/lorenzodifuccia/http.server
Project-URL: Bug Tracker, https://github.com/lorenzodifuccia/http.server/issues
Classifier: Intended Audience :: Developers
Classifier: Intended Audience :: System Administrators
Classifier: Programming Language :: Python :: 3
Classifier: Framework :: Flask
Classifier: Operating System :: OS Independent
Classifier: License :: OSI Approved :: Apache Software License
Requires-Python: >=3.7
License-File: LICENSE
Requires-Dist: Flask (>=2.2.2)
Requires-Dist: humanize (>=4.4.0)
Requires-Dist: waitress (>=2.1.2)
